{
  "run_id": "18b4238b6435",
  "run_ts": "2026-07-12 08:28:28.742648+00:00",
  "status": "success",
  "rows_ingested": 48,
  "checks_passed": 13,
  "checks_failed": 0,
  "anomalies_found": 0,
  "error": null,
  "total_rows_in_lake": 192,
  "contract": {
    "passed": true,
    "checks_passed": 13,
    "checks_failed": 0,
    "failure_cases": []
  },
  "metrics": [
    {
      "run_id": "18b4238b6435",
      "run_ts": "2026-07-12 08:28:28.742648+00:00",
      "metric": "freshness",
      "column_name": "minutes",
      "value": -871.5209558666667,
      "baseline": 180.0,
      "zscore": NaN,
      "is_anomaly": false
    },
    {
      "run_id": "18b4238b6435",
      "run_ts": "2026-07-12 08:28:28.742648+00:00",
      "metric": "volume",
      "column_name": "row_count",
      "value": 48.0,
      "baseline": 48.0,
      "zscore": 0.0,
      "is_anomaly": false
    },
    {
      "run_id": "18b4238b6435",
      "run_ts": "2026-07-12 08:28:28.742648+00:00",
      "metric": "schema_drift",
      "column_name": "columns",
      "value": 0.0,
      "baseline": 0.0,
      "zscore": NaN,
      "is_anomaly": false
    },
    {
      "run_id": "18b4238b6435",
      "run_ts": "2026-07-12 08:28:28.742648+00:00",
      "metric": "distribution_drift",
      "column_name": "temperature_2m",
      "value": 22.508333333333336,
      "baseline": 19.965104166666666,
      "zscore": 2.028808917184088,
      "is_anomaly": false
    },
    {
      "run_id": "18b4238b6435",
      "run_ts": "2026-07-12 08:28:28.742648+00:00",
      "metric": "distribution_drift",
      "column_name": "relative_humidity_2m",
      "value": 52.25,
      "baseline": 58.848958333333336,
      "zscore": -2.17987967438762,
      "is_anomaly": false
    },
    {
      "run_id": "18b4238b6435",
      "run_ts": "2026-07-12 08:28:28.742648+00:00",
      "metric": "distribution_drift",
      "column_name": "wind_speed_10m",
      "value": 9.766666666666666,
      "baseline": 11.595833333333333,
      "zscore": -0.8233592364062915,
      "is_anomaly": false
    },
    {
      "run_id": "18b4238b6435",
      "run_ts": "2026-07-12 08:28:28.742648+00:00",
      "metric": "distribution_drift",
      "column_name": "pressure_msl",
      "value": 1019.8416666666667,
      "baseline": 1016.6841666666667,
      "zscore": 1.8173811036754217,
      "is_anomaly": false
    },
    {
      "run_id": "18b4238b6435",
      "run_ts": "2026-07-12 08:28:28.742648+00:00",
      "metric": "contract_violations",
      "column_name": "checks_failed",
      "value": 0.0,
      "baseline": 0.0,
      "zscore": NaN,
      "is_anomaly": false
    }
  ]
}