{
  "run_id": "43df0a393294",
  "run_ts": "2026-07-23 11:15:01.739015+00:00",
  "status": "success",
  "rows_ingested": 48,
  "checks_passed": 13,
  "checks_failed": 0,
  "anomalies_found": 0,
  "error": null,
  "total_rows_in_lake": 456,
  "contract": {
    "passed": true,
    "checks_passed": 13,
    "checks_failed": 0,
    "failure_cases": []
  },
  "metrics": [
    {
      "run_id": "43df0a393294",
      "run_ts": "2026-07-23 11:15:01.739015+00:00",
      "metric": "freshness",
      "column_name": "minutes",
      "value": -704.9710164166667,
      "baseline": 180.0,
      "zscore": NaN,
      "is_anomaly": false
    },
    {
      "run_id": "43df0a393294",
      "run_ts": "2026-07-23 11:15:01.739015+00:00",
      "metric": "volume",
      "column_name": "row_count",
      "value": 48.0,
      "baseline": 48.0,
      "zscore": 0.0,
      "is_anomaly": false
    },
    {
      "run_id": "43df0a393294",
      "run_ts": "2026-07-23 11:15:01.739015+00:00",
      "metric": "schema_drift",
      "column_name": "columns",
      "value": 0.0,
      "baseline": 0.0,
      "zscore": NaN,
      "is_anomaly": false
    },
    {
      "run_id": "43df0a393294",
      "run_ts": "2026-07-23 11:15:01.739015+00:00",
      "metric": "distribution_drift",
      "column_name": "temperature_2m",
      "value": 16.725,
      "baseline": 17.171458333333327,
      "zscore": -1.2901655911937329,
      "is_anomaly": false
    },
    {
      "run_id": "43df0a393294",
      "run_ts": "2026-07-23 11:15:01.739015+00:00",
      "metric": "distribution_drift",
      "column_name": "relative_humidity_2m",
      "value": 71.20833333333333,
      "baseline": 64.340625,
      "zscore": 1.8780708446821002,
      "is_anomaly": false
    },
    {
      "run_id": "43df0a393294",
      "run_ts": "2026-07-23 11:15:01.739015+00:00",
      "metric": "distribution_drift",
      "column_name": "wind_speed_10m",
      "value": 13.050000000000002,
      "baseline": 12.465833333333336,
      "zscore": 1.2260035001436838,
      "is_anomaly": false
    },
    {
      "run_id": "43df0a393294",
      "run_ts": "2026-07-23 11:15:01.739015+00:00",
      "metric": "distribution_drift",
      "column_name": "pressure_msl",
      "value": 1016.0145833333332,
      "baseline": 1017.9641666666666,
      "zscore": -1.6434172080858203,
      "is_anomaly": false
    },
    {
      "run_id": "43df0a393294",
      "run_ts": "2026-07-23 11:15:01.739015+00:00",
      "metric": "contract_violations",
      "column_name": "checks_failed",
      "value": 0.0,
      "baseline": 0.0,
      "zscore": NaN,
      "is_anomaly": false
    }
  ]
}