{
  "run_id": "0599450951ca",
  "run_ts": "2026-07-15 19:19:16.851001+00:00",
  "status": "success",
  "rows_ingested": 48,
  "checks_passed": 13,
  "checks_failed": 0,
  "anomalies_found": 0,
  "error": null,
  "total_rows_in_lake": 264,
  "contract": {
    "passed": true,
    "checks_passed": 13,
    "checks_failed": 0,
    "failure_cases": []
  },
  "metrics": [
    {
      "run_id": "0599450951ca",
      "run_ts": "2026-07-15 19:19:16.851001+00:00",
      "metric": "freshness",
      "column_name": "minutes",
      "value": -220.71914998333332,
      "baseline": 180.0,
      "zscore": NaN,
      "is_anomaly": false
    },
    {
      "run_id": "0599450951ca",
      "run_ts": "2026-07-15 19:19:16.851001+00:00",
      "metric": "volume",
      "column_name": "row_count",
      "value": 48.0,
      "baseline": 48.0,
      "zscore": 0.0,
      "is_anomaly": false
    },
    {
      "run_id": "0599450951ca",
      "run_ts": "2026-07-15 19:19:16.851001+00:00",
      "metric": "schema_drift",
      "column_name": "columns",
      "value": 0.0,
      "baseline": 0.0,
      "zscore": NaN,
      "is_anomaly": false
    },
    {
      "run_id": "0599450951ca",
      "run_ts": "2026-07-15 19:19:16.851001+00:00",
      "metric": "distribution_drift",
      "column_name": "temperature_2m",
      "value": 21.195833333333333,
      "baseline": 22.07125,
      "zscore": -0.9364841736748191,
      "is_anomaly": false
    },
    {
      "run_id": "0599450951ca",
      "run_ts": "2026-07-15 19:19:16.851001+00:00",
      "metric": "distribution_drift",
      "column_name": "relative_humidity_2m",
      "value": 54.583333333333336,
      "baseline": 57.35104166666665,
      "zscore": -0.8439246192666588,
      "is_anomaly": false
    },
    {
      "run_id": "0599450951ca",
      "run_ts": "2026-07-15 19:19:16.851001+00:00",
      "metric": "distribution_drift",
      "column_name": "wind_speed_10m",
      "value": 8.7875,
      "baseline": 9.809166666666666,
      "zscore": -1.070738682850591,
      "is_anomaly": false
    },
    {
      "run_id": "0599450951ca",
      "run_ts": "2026-07-15 19:19:16.851001+00:00",
      "metric": "distribution_drift",
      "column_name": "pressure_msl",
      "value": 1020.7750000000001,
      "baseline": 1020.6623958333336,
      "zscore": 0.49265912972915576,
      "is_anomaly": false
    },
    {
      "run_id": "0599450951ca",
      "run_ts": "2026-07-15 19:19:16.851001+00:00",
      "metric": "contract_violations",
      "column_name": "checks_failed",
      "value": 0.0,
      "baseline": 0.0,
      "zscore": NaN,
      "is_anomaly": false
    }
  ]
}